{
    "net_attr": {
        "activation": "signal", 
        "bias": -3.0, 
        "lrn_rate": 0.3, 
        "weights": [
            1.681344601898964, 
            7.691410561376823
        ]
    }, 
    "net_params": {
        "a": -5.0, 
        "b": 2.0, 
        "epochs": 10, 
        "lrn_rate": 0.3, 
        "max_error": 0.015, 
        "num_test": 100, 
        "num_training": 1000, 
        "num_validation": 1000, 
        "type": "perceptron"
    }, 
    "test_error": 0.01, 
    "validation_error": [
        true, 
        0.007
    ]
}